cavalry/__init__.py
cavalry/__main__.py
cavalry/errors.py
cavalry-2.1.1.data/scripts/cav
cavalry-2.1.1.dist-info/LICENSE
cavalry-2.1.1.dist-info/METADATA
cavalry-2.1.1.dist-info/WHEEL
cavalry-2.1.1.dist-info/top_level.txt
cavalry-2.1.1.dist-info/RECORD
