Metadata-Version: 2.1
Name: cavalry
Version: 2.1.1
Summary: Secrets manager
Home-page: https://github.com/seanchristians/cavalry
Author: Sean Christians
Author-email: seanchristians.scc@gmail.com
License: UNKNOWN
Platform: UNKNOWN
Classifier: License :: OSI Approved :: GNU Affero General Public License v3
Classifier: Natural Language :: English
Classifier: Operating System :: Unix
Classifier: Programming Language :: Python :: 3.8
Requires-Python: >=3.8
